pelican_zopfli.py
pelican_zopfli-1.0.1.dist-info/LICENSE.md
pelican_zopfli-1.0.1.dist-info/METADATA
pelican_zopfli-1.0.1.dist-info/WHEEL
pelican_zopfli-1.0.1.dist-info/top_level.txt
pelican_zopfli-1.0.1.dist-info/RECORD
