Metadata-Version: 2.1
Name: pelican-zopfli
Version: 1.0.1
Summary: An static resource compression plugin for Pelican, the static site generator.
Home-page: https://github.com/VorpalBlade/pelican_zopfli
Author: Arvid Norlander
Author-email: VorpalBlade@users.noreply.github.com
License: AGPL-3.0
Keywords: pelican blog static compress zopfli
Platform: UNKNOWN
Classifier: Programming Language :: Python :: 3
Classifier: License :: OSI Approved :: GNU Affero General Public License v3 or later (AGPLv3+)
Classifier: Operating System :: OS Independent
Classifier: Framework :: Pelican :: Plugins
Requires-Dist: zopflipy (>=1.1)
Requires-Dist: pelican (>=4.0)
Requires-Dist: joblib (>=0.13.2)
